Workbook

Sheet Forecast
A1: observation_date | B1: WTISPLC | C1: Forecast(WTISPLC) | D1: Lower Confidence Bound(WTISPLC) | E1: Upper Confidence Bound(WTISPLC) | G1: Statistic | H1: Value
A2: 16803 | B2: 1.17 | G2: Alpha | H2: =_xlfn.FORECAST.ETS.STAT($B$2:$B$950,$A$2:$A$950,1,12,1) -> 0.251
A3: 16834 | B3: 1.17 | G3: Beta | H3: =_xlfn.FORECAST.ETS.STAT($B$2:$B$950,$A$2:$A$950,2,12,1) -> 0.001
A4: 16862 | B4: 1.17 | G4: Gamma | H4: =_xlfn.FORECAST.ETS.STAT($B$2:$B$950,$A$2:$A$950,3,12,1) -> 0.001
A5: 16893 | B5: 1.27 | G5: MASE | H5: =_xlfn.FORECAST.ETS.STAT($B$2:$B$950,$A$2:$A$950,4,12,1) -> 7.4139272
A6: 16923 | B6: 1.27 | G6: SMAPE | H6: =_xlfn.FORECAST.ETS.STAT($B$2:$B$950,$A$2:$A$950,5,12,1) -> 0.10603186
A7: 16954 | B7: 1.27 | G7: MAE | H7: =_xlfn.FORECAST.ETS.STAT($B$2:$B$950,$A$2:$A$950,6,12,1) -> 6.9800071
A8: 16984 | B8: 1.27 | G8: RMSE | H8: =_xlfn.FORECAST.ETS.STAT($B$2:$B$950,$A$2:$A$950,7,12,1) -> 9.4545166
A9: 17015 | B9: 1.52
A10: 17046 | B10: 1.52
A11: 17076 | B11: 1.52
A12: 17107 | B12: 1.52
A13: 17137 | B13: 1.62
A14: 17168 | B14: 1.62
A15: 17199 | B15: 1.62
A16: 17227 | B16: 1.62
A17: 17258 | B17: 1.87
A18: 17288 | B18: 1.87
A19: 17319 | B19: 1.87
A20: 17349 | B20: 1.87
... A949: 45627 | B949: 70.12
A950: 45658 | B950: 75.74 | C950: 75.74 | D950: 75.74 | E950: 75.74
A951: 45689 | C951: =_xlfn.FORECAST.ETS(A951,$B$2:$B$950,$A$2:$A$950,12,1) -> 74.413452 | D951: =C951-_xlfn.FORECAST.ETS.CONFINT(A951,$B$2:$B$950,$A$2:$A$950,0.95,12,1) -> 62.581256 | E951: =C951+_xlfn.FORECAST.ETS.CONFINT(A951,$B$2:$B$950,$A$2:$A$950,0.95,12,1) -> 86.245648
A952: 45717 | C952: =_xlfn.FORECAST.ETS(A952,$B$2:$B$950,$A$2:$A$950,12,1) -> 74.539667 | D952: =C952-_xlfn.FORECAST.ETS.CONFINT(A952,$B$2:$B$950,$A$2:$A$950,0.95,12,1) -> 62.337557 | E952: =C952+_xlfn.FORECAST.ETS.CONFINT(A952,$B$2:$B$950,$A$2:$A$950,0.95,12,1) -> 86.741776
A953: 45748 | C953: =_xlfn.FORECAST.ETS(A953,$B$2:$B$950,$A$2:$A$950,12,1) -> 74.72657 | D953: =C953-_xlfn.FORECAST.ETS.CONFINT(A953,$B$2:$B$950,$A$2:$A$950,0.95,12,1) -> 62.162621 | E953: =C953+_xlfn.FORECAST.ETS.CONFINT(A953,$B$2:$B$950,$A$2:$A$950,0.95,12,1) -> 87.290518
A954: 45778 | C954: =_xlfn.FORECAST.ETS(A954,$B$2:$B$950,$A$2:$A$950,12,1) -> 74.808915 | D954: =C954-_xlfn.FORECAST.ETS.CONFINT(A954,$B$2:$B$950,$A$2:$A$950,0.95,12,1) -> 61.890513 | E954: =C954+_xlfn.FORECAST.ETS.CONFINT(A954,$B$2:$B$950,$A$2:$A$950,0.95,12,1) -> 87.727316
A955: 45809 | C955: =_xlfn.FORECAST.ETS(A955,$B$2:$B$950,$A$2:$A$950,12,1) -> 74.782369 | D955: =C955-_xlfn.FORECAST.ETS.CONFINT(A955,$B$2:$B$950,$A$2:$A$950,0.95,12,1) -> 61.516298 | E955: =C955+_xlfn.FORECAST.ETS.CONFINT(A955,$B$2:$B$950,$A$2:$A$950,0.95,12,1) -> 88.04844
A956: 45839 | C956: =_xlfn.FORECAST.ETS(A956,$B$2:$B$950,$A$2:$A$950,12,1) -> 74.840366 | D956: =C956-_xlfn.FORECAST.ETS.CONFINT(A956,$B$2:$B$950,$A$2:$A$950,0.95,12,1) -> 61.232878 | E956: =C956+_xlfn.FORECAST.ETS.CONFINT(A956,$B$2:$B$950,$A$2:$A$950,0.95,12,1) -> 88.447855
A957: 45870 | C957: =_xlfn.FORECAST.ETS(A957,$B$2:$B$950,$A$2:$A$950,12,1) -> 74.94538 | D957: =C957-_xlfn.FORECAST.ETS.CONFINT(A957,$B$2:$B$950,$A$2:$A$950,0.95,12,1) -> 61.002257 | E957: =C957+_xlfn.FORECAST.ETS.CONFINT(A957,$B$2:$B$950,$A$2:$A$950,0.95,12,1) -> 88.888502
A958: 45901 | C958: =_xlfn.FORECAST.ETS(A958,$B$2:$B$950,$A$2:$A$950,12,1) -> 74.993044 | D958: =C958-_xlfn.FORECAST.ETS.CONFINT(A958,$B$2:$B$950,$A$2:$A$950,0.95,12,1) -> 60.719653 | E958: =C958+_xlfn.FORECAST.ETS.CONFINT(A958,$B$2:$B$950,$A$2:$A$950,0.95,12,1) -> 89.266434
A959: 45931 | C959: =_xlfn.FORECAST.ETS(A959,$B$2:$B$950,$A$2:$A$950,12,1) -> 75.041626 | D959: =C959-_xlfn.FORECAST.ETS.CONFINT(A959,$B$2:$B$950,$A$2:$A$950,0.95,12,1) -> 60.442959 | E959: =C959+_xlfn.FORECAST.ETS.CONFINT(A959,$B$2:$B$950,$A$2:$A$950,0.95,12,1) -> 89.640293
A960: 45962 | C960: =_xlfn.FORECAST.ETS(A960,$B$2:$B$950,$A$2:$A$950,12,1) -> 75.108383 | D960: =C960-_xlfn.FORECAST.ETS.CONFINT(A960,$B$2:$B$950,$A$2:$A$950,0.95,12,1) -> 60.189096 | E960: =C960+_xlfn.FORECAST.ETS.CONFINT(A960,$B$2:$B$950,$A$2:$A$950,0.95,12,1) -> 90.027671
A961: 45992 | C961: =_xlfn.FORECAST.ETS(A961,$B$2:$B$950,$A$2:$A$950,12,1) -> 75.155534 | D961: =C961-_xlfn.FORECAST.ETS.CONFINT(A961,$B$2:$B$950,$A$2:$A$950,0.95,12,1) -> 59.919979 | E961: =C961+_xlfn.FORECAST.ETS.CONFINT(A961,$B$2:$B$950,$A$2:$A$950,0.95,12,1) -> 90.391089
A962: 46023 | C962: =_xlfn.FORECAST.ETS(A962,$B$2:$B$950,$A$2:$A$950,12,1) -> 75.443082 | D962: =C962-_xlfn.FORECAST.ETS.CONFINT(A962,$B$2:$B$950,$A$2:$A$950,0.95,12,1) -> 59.895338 | E962: =C962+_xlfn.FORECAST.ETS.CONFINT(A962,$B$2:$B$950,$A$2:$A$950,0.95,12,1) -> 90.990826
... A1258: 55032 | C1258: =_xlfn.FORECAST.ETS(A1258,$B$2:$B$950,$A$2:$A$950,12,1) -> 103.24471 | D1258: =C1258-_xlfn.FORECAST.ETS.CONFINT(A1258,$B$2:$B$950,$A$2:$A$950,0.95,12,1) -> 16.467644 | E1258: =C1258+_xlfn.FORECAST.ETS.CONFINT(A1258,$B$2:$B$950,$A$2:$A$950,0.95,12,1) -> 190.02177
C1259: =AVERAGE(C950:C1258) -> 88.796123 | D1259: =AVERAGE(D950:D1258) -> 38.907292 | E1259: =AVERAGE(E950:E1258) -> 138.68495

Sheet Data_Crude_Oil_For_Forecasting
A1: observation_date | B1: WTISPLC
A2: 16803 | B2: 1.17
A3: 16834 | B3: 1.17
A4: 16862 | B4: 1.17
A5: 16893 | B5: 1.27
A6: 16923 | B6: 1.27
A7: 16954 | B7: 1.27
A8: 16984 | B8: 1.27
A9: 17015 | B9: 1.52
A10: 17046 | B10: 1.52
A11: 17076 | B11: 1.52
A12: 17107 | B12: 1.52
A13: 17137 | B13: 1.62
... A950: 45658 | B950: 75.74

Sheet Scenario Summary
B2: Scenario Summary
D3: Current Values: | E3: optimistic | F3: pessimistic
E4: Created by Anvar on 20/7/2026 | F4: Created by Anvar on 20/7/2026
B5: Changing Cells:
C6: $B$6 | D6: 0 | E6: 0 | F6: 0
C7: $C$6 | D7: 35007 | E7: 35007 | F7: 15150.77
C8: $D$6 | D8: 41572.24 | E8: 41572.24 | F8: 13386.41
C9: $E$6 | D9: 49105.1 | E9: 49105.1 | F9: 11871.78
C10: $F$6 | D10: 57795.91 | E10: 57795.91 | F10: 10548.59
C11: $G$6 | D11: 67846.8 | E11: 67846.8 | F11: 9381.25
C12: $B$14 | D12: 0 | E12: 0 | F12: 0
C13: $C$14 | D13: 29920.51 | E13: 29920.51 | F13: 12949.37
C14: $D$14 | D14: 35531.83 | E14: 35531.83 | F14: 11441.38
C15: $E$14 | D15: 41970.17 | E15: 41970.17 | F15: 10146.82
C16: $F$14 | D16: 49398.22 | E16: 49398.22 | F16: 9015.89
C17: $G$14 | D17: 57988.72 | E17: 57988.72 | F17: 8018.16
B18: Result Cells:
C19: $B$10 | D19: 7400 | E19: 7400 | F19: 7400
C20: $C$10 | D20: 42671 | E20: 42671 | F20: 22814.77
C21: $D$10 | D21: 49510.26 | E21: 49510.26 | F21: 21324.43
C22: $E$10 | D22: 57327.566 | E22: 57327.566 | F22: 20094.246
C23: $F$10 | D23: 66313.67 | E23: 66313.67 | F23: 19066.35
C24: $G$10 | D24: 76671.144 | E24: 76671.144 | F24: 18205.594
C25: $B$21 | D25: 6261 | E25: 6261 | F25: 6261
C26: $C$21 | D26: 11573.54 | E26: 11573.54 | F26: 8688.45
C27: $D$21 | D27: 12776.983 | E27: 12776.983 | F27: 8681.6025
C28: $E$21 | D28: 14119.826 | E28: 14119.826 | F28: 8709.8557
C29: $F$21 | D29: 15641.051 | E29: 15641.051 | F29: 8776.0614
C30: $G$21 | D30: 17368.406 | E30: 17368.406 | F30: 8873.4156
B31: Notes: Current Values column represents values of changing cells at
B32: time Scenario Summary Report was created. Changing cells for each
B33: scenario are highlighted in gray.

Sheet Net_Receivable
A1: Net Receivable Statement
A2: Particulars | B2: 45658 | C2: 46023 | D2: 46388 | E2: 46753 | F2: 47119 | G2: 47484
A4: Incomes
A6: Refined Petroleum Sales Revenue | B6: 0 | C6: 35007 | D6: 41572.24 | E6: 49105.1 | F6: 57795.91 | G6: 67846.8
A7: Renewable Energy Revenue | B7: 5300 | C7: =B7+(B7*3%) -> 5459 | D7: =C7+(C7*3%) -> 5622.77 | E7: =D7+(D7*3%) -> 5791.4531 | F7: =E7+(E7*3%) -> 5965.1967 | G7: =F7+(F7*3%) -> 6144.1526 | I7: Renewable Energy Revenue is increasing by 3% and is constant throughout the year
A8: Service Charges Revenue | B8: 2100 | C8: =B8+(B8*5%) -> 2205 | D8: =C8+(C8*5%) -> 2315.25 | E8: =D8+(D8*5%) -> 2431.0125 | F8: =E8+(E8*5%) -> 2552.5631 | G8: =F8+(F8*5%) -> 2680.1913 | I8: Service Charges Revenue is increasing by 5% and is constant throughout the year
A10: Total Revenue | B10: =SUM(B6:B8) -> 7400 | C10: =SUM(C6:C8) -> 42671 | D10: =SUM(D6:D8) -> 49510.26 | E10: =SUM(E6:E8) -> 57327.566 | F10: =SUM(F6:F8) -> 66313.67 | G10: =SUM(G6:G8) -> 76671.144
A12: Expenses
A14: Material Expenses | B14: 0 | C14: 29920.51 | D14: 35531.83 | E14: 41970.17 | F14: 49398.22 | G14: 57988.72
A15: Labor Expenses | B15: 619 | C15: =B15+(B15*5%) -> 649.95 | D15: =C15+(C15*5%) -> 682.4475 | E15: =D15+(D15*5%) -> 716.56988 | F15: =E15+(E15*5%) -> 752.39837 | G15: =F15+(F15*5%) -> 790.01829 | I15: Labour Expenses is increasing by 3% and is constant throughout the year
A16: Fixed Expenses | B16: 400 | C16: 400 | D16: 400 | E16: 400 | F16: 400 | G16: 400
A17: Variable Expenses | B17: 120 | C17: 127 | D17: 119 | E17: 121 | F17: 122 | G17: 124
A19: Total Expenses | B19: =SUM(B14:B17) -> 1139 | C19: =SUM(C14:C17) -> 31097.46 | D19: =SUM(D14:D17) -> 36733.278 | E19: =SUM(E14:E17) -> 43207.74 | F19: =SUM(F14:F17) -> 50672.618 | G19: =SUM(G14:G17) -> 59302.738
A21: Net Profit | B21: =B10-B19 -> 6261 | C21: =C10-C19 -> 11573.54 | D21: =D10-D19 -> 12776.982 | E21: =E10-E19 -> 14119.826 | F21: =F10-F19 -> 15641.051 | G21: =G10-G19 -> 17368.406
A23: Optimistic Scenario
A24: Optimistic Scenario | B24: 45658 | C24: 46023 | D24: 46388 | E24: 46753 | F24: 47119 | G24: 47484
A25: Upper Confidence Level | B25: =Calculations!B18 -> 0 | C25: =Calculations!C18 -> 90.990826 | D25: =Calculations!D18 -> 95.624182 | E25: =Calculations!E18 -> 99.956814 | F25: =Calculations!F18 -> 104.11289 | G25: =Calculations!G18 -> 108.15791
A26: Units Sold- Optimistic | B26: 291 | C26: =Calculations!C19 -> 328.83 | D26: =Calculations!D19 -> 371.5779 | E26: =Calculations!E19 -> 419.88303 | F26: =Calculations!F19 -> 474.46782 | G26: =Calculations!G19 -> 536.14864
A28: Calculation Refined Petroleum Sales Revenue | B28: 45658 | C28: 46023 | D28: 46388 | E28: 46753 | F28: 47119 | G28: 47484
A29: Premium for Refined Petroleum Products | B29: 0.17 | C29: 0.17 | D29: 0.17 | E29: 0.17 | F29: 0.17 | G29: 0.17
A30: Price per Refined Petroleum Unit | B30: =Calculations!B23 -> 0 | C30: =Calculations!C23 -> 106.45927 | D30: =Calculations!D23 -> 111.88029 | E30: =Calculations!E23 -> 116.94947 | F30: =Calculations!F23 -> 121.81208 | G30: =Calculations!G23 -> 126.54476
A31: Total Refined Petroleum Sales | B31: =Calculations!B24 -> 0 | C31: =Calculations!C24 -> 35007.001 | D31: =Calculations!D24 -> 41572.244 | E31: =Calculations!E24 -> 49105.099 | F31: =Calculations!F24 -> 57795.912 | G31: =Calculations!G24 -> 67846.799
A33: Calculation Material Expenses | B33: 45658 | C33: 46023 | D33: 46388 | E33: 46753 | F33: 47119 | G33: 47484
A34: Inventory (Units Sold) | B34: =B26 -> 291 | C34: =C26 -> 328.83 | D34: =D26 -> 371.5779 | E34: =E26 -> 419.88303 | F34: =F26 -> 474.46782 | G34: =G26 -> 536.14864
A35: Raw Crude Price | B35: =Calculations!B28 -> 0 | C35: =Calculations!C28 -> 90.990826 | D35: =Calculations!D28 -> 95.624182 | E35: =Calculations!E28 -> 99.956814 | F35: =Calculations!F28 -> 104.11289 | G35: =Calculations!G28 -> 108.15791
A36: Total Material Expenses | B36: =Calculations!B29 -> 0 | C36: =Calculations!C29 -> 29920.513 | D36: =Calculations!D29 -> 35531.833 | E36: =Calculations!E29 -> 41970.17 | F36: =Calculations!F29 -> 49398.216 | G36: =Calculations!G29 -> 57988.717
A38: Pessimistic Scenario
A39: Pessimistic Scenario | B39: 45658 | C39: 46023 | D39: 46388 | E39: 46753 | F39: 47119 | G39: 47484
A40: Lower Confidence Level | B40: =Calculations!B32 -> 0 | C40: =Calculations!C32 -> 59.895338 | D40: =Calculations!D32 -> 57.522115 | E40: =Calculations!E32 -> 55.449616 | F40: =Calculations!F32 -> 53.553673 | G40: =Calculations!G32 -> 51.768784
A41: Units Sold - Pessimistic | B41: =Calculations!B33 -> 235 | C41: =Calculations!C33 -> 216.2 | D41: =Calculations!D33 -> 198.904 | E41: =Calculations!E33 -> 182.99168 | F41: =Calculations!F33 -> 168.35235 | G41: =Calculations!G33 -> 154.88416
A43: Calculation Refined Petroleum Sales Revenue | B43: 45658 | C43: 46023 | D43: 46388 | E43: 46753 | F43: 47119 | G43: 47484
A44: Premium for Refined Petroleum Products | B44: 0.17 | C44: 0.17 | D44: 0.17 | E44: 0.17 | F44: 0.17 | G44: 0.17
A45: Price per Refined Petroleum Unit | B45: =Calculations!B37 -> 0 | C45: =Calculations!C37 -> 70.077545 | D45: =Calculations!D37 -> 67.300874 | E45: =Calculations!E37 -> 64.87605 | F45: =Calculations!F37 -> 62.657798 | G45: =Calculations!G37 -> 60.569477
A46: Total Refined Petroleum Sales | B46: =Calculations!B38 -> 0 | C46: =Calculations!C38 -> 15150.765 | D46: =Calculations!D38 -> 13386.413 | E46: =Calculations!E38 -> 11871.777 | F46: =Calculations!F38 -> 10548.587 | G46: =Calculations!G38 -> 9381.2524
A48: Calculation Material Expenses | B48: 45658 | C48: 46023 | D48: 46388 | E48: 46753 | F48: 47119 | G48: 47484
A49: Inventory (Units Sold) | B49: =B41 -> 235 | C49: =C41 -> 216.2 | D49: =D41 -> 198.904 | E49: =E41 -> 182.99168 | F49: =F41 -> 168.35235 | G49: =G41 -> 154.88416
A50: Raw Crude Price | B50: =B40 -> 0 | C50: =C40 -> 59.895338 | D50: =D40 -> 57.522115 | E50: =E40 -> 55.449616 | F50: =F40 -> 53.553673 | G50: =G40 -> 51.768784
A51: Total Material Expenses | B51: =B49*B50 -> 0 | C51: =C49*C50 -> 12949.372 | D51: =D49*D50 -> 11441.379 | E51: =E49*E50 -> 10146.818 | F51: =F49*F50 -> 9015.8865 | G51: =G49*G50 -> 8018.1645

Sheet Calculations
A1: Notes to Consider
A2: 46023
A3: Current Scenario | B3: 45658 | C3: 46023 | D3: 46388 | E3: 46753 | F3: 47119 | G3: 47484 | H3: 47849 | I3: 48214 | J3: 48580 | K3: 48945 | L3: 49310 | N3: Note:
A4: Current Crude Price | B4: 75.74 | C4: =VLOOKUP(A2,Forecast!A1:E975,3,FALSE) -> 75.443082 | D4: =VLOOKUP(D3,Forecast!A1:E1014,3,FALSE) -> 76.573148 | E4: =VLOOKUP(E3,Forecast!A1:E1090,3,FALSE) -> 77.703215 | F4: =VLOOKUP(F3,Forecast!A1:E1245,3,FALSE) -> 78.833281 | G4: =VLOOKUP(G3,Forecast!A1:E1039,3,FALSE) -> 79.963348 | H4: =VLOOKUP(H3,#REF!,3,FALSE) -> #REF! | I4: =VLOOKUP(I3,#REF!,3,FALSE) -> #REF! | J4: =VLOOKUP(J3,#REF!,3,FALSE) -> #REF! | K4: =VLOOKUP(K3,#REF!,3,FALSE) -> #REF! | L4: =VLOOKUP(L3,#REF!,3,FALSE) -> #REF! | N4: You will have to use the VLOOKUP Function here or manually enter the figures from the forecasting sheet
A5: Units Sold | B5: 267 | C5: =B5*1.1 -> 293.7 | D5: =C5*1.1 -> 323.07 | E5: =D5*1.1 -> 355.377 | F5: =E5*1.1 -> 390.9147 | G5: =F5*1.1 -> 430.00617 | H5: =$B$5+(1.1)^6 -> 268.77156 | I5: =$B$5+(1.1)^7 -> 268.94872 | J5: =$B$5+(1.1)^8 -> 269.14359 | K5: =$B$5+(1.1)^9 -> 269.35795 | L5: =$B$5+(1.1)^10 -> 269.59374 | N5: The Units sold is increasing by 10% every year
A7: Calculation Refined Petroleum Sales Revenue | B7: 45658 | C7: 46023 | D7: 46388 | E7: 46753 | F7: 47119 | G7: 47484 | H7: 47849 | I7: 48214 | J7: 48580 | K7: 48945 | L7: 49310
A8: Premium for Refined Petroleum Products | B8: 0.17 | C8: 0.17 | D8: 0.17 | E8: 0.17 | F8: 0.17 | G8: 0.17 | H8: 0.17 | I8: 0.17 | J8: 0.17 | K8: 0.17 | L8: 0.17 | N8: Premium of the Refined Petroleum Products remain constant
A9: Price per Refined Petroleum Unit | B9: =B4+(B4*B8) -> 88.6158 | C9: =C4+(C4*C8) -> 88.268406 | D9: =D4+(D4*D8) -> 89.590584 | E9: =E4+(E4*E8) -> 90.912761 | F9: =F4+(F4*F8) -> 92.234939 | G9: =G4+(G4*G8) -> 93.557117 | H9: =H4+(H4*17%) -> #REF! | I9: =I4+(I4*17%) -> #REF! | J9: =J4+(J4*17%) -> #REF! | K9: =K4+(K4*17%) -> #REF! | L9: =L4+(L4*17%) -> #REF! | N9: You will have to add 17% premium on the Current Crude Price
A10: Total Refined Petroleum Sales | B10: =B9*B5 -> 23660.419 | C10: =C9*C5 -> 25924.431 | D10: =D9*D5 -> 28944.03 | E10: =E9*E5 -> 32308.304 | F10: =F9*F5 -> 36055.994 | G10: =G9*G5 -> 40230.138 | H10: =H9*H5 -> #REF! | I10: =I9*I5 -> #REF! | ... L10: =L9*L5 -> #REF! | N10: To find the Total Refined Petroleum Sales you will have to multiply the Units Sold with Price per Refined Petroleum Unit
A12: Calculation Material Expenses | B12: 45658 | C12: 46023 | D12: 46388 | E12: 46753 | F12: 47119 | G12: 47484 | H12: 47849 | I12: 48214 | J12: 48580 | K12: 48945 | L12: 49310
A13: Inventory (Units Sold) | B13: =B5 -> 267 | C13: =C5 -> 293.7 | D13: =D5 -> 323.07 | E13: =E5 -> 355.377 | F13: =F5 -> 390.9147 | G13: =G5 -> 430.00617 | H13: =H5 -> 268.77156 | I13: =I5 -> 268.94872 | ... L13: =L5 -> 269.59374 | N13: It’s the same as Units Sold
A14: Raw Crude Price | B14: =B4 -> 75.74 | C14: =C4 -> 75.443082 | D14: =D4 -> 76.573148 | E14: =E4 -> 77.703215 | F14: =F4 -> 78.833281 | G14: =G4 -> 79.963348 | H14: =H4 -> #REF! | I14: =I4 -> #REF! | ... L14: =L4 -> #REF! | N14: Is the the same as Current Crude Price
A15: Total Material Expenses | B15: =B13*B14 -> 20222.58 | C15: =C13*C14 -> 22157.633 | D15: =D13*D14 -> 24738.487 | E15: =E13*E14 -> 27613.935 | F15: =F13*F14 -> 30817.089 | G15: =G13*G14 -> 34384.733 | H15: =H13*H14 -> #REF! | I15: =I13*I14 -> #REF! | ... L15: =L13*L14 -> #REF! | N15: Total Material Expenses is when you will have to multiply Raw Crude Price with Units sold.
A17: Optimistic Scenario | B17: 45658 | C17: 46023 | D17: 46388 | E17: 46753 | F17: 47119 | G17: 47484 | H17: 47849 | I17: 48214 | J17: 48580 | K17: 48945 | L17: 49310
A18: Upper Confidence Level | C18: =VLOOKUP(C17,Forecast!A1:E1135,5,FALSE) -> 90.990826 | D18: =VLOOKUP(D17,Forecast!A1:E1182,5,FALSE) -> 95.624182 | E18: =VLOOKUP(E17,Forecast!A1:E1126,5,FALSE) -> 99.956814 | F18: =VLOOKUP(F17,Forecast!A1:E1237,5,FALSE) -> 104.11289 | G18: =VLOOKUP(G17,Forecast!A1:E1061,5,FALSE) -> 108.15791 | H18: =VLOOKUP(H3,#REF!,5,0) -> #REF! | I18: =VLOOKUP(I3,#REF!,5,0) -> #REF! | J18: =VLOOKUP(J3,#REF!,5,0) -> #REF! | K18: =VLOOKUP(K3,#REF!,5,0) -> #REF! | L18: =VLOOKUP(L3,#REF!,5,0) -> #REF! | N18: You will have to use the VLOOKUP Function here or manually enter the figures from the forecasting sheet
A19: Units Sold- Optimistic | B19: 291 | C19: =B19*1.13 -> 328.83 | D19: =C19*1.13 -> 371.5779 | E19: =D19*1.13 -> 419.88303 | F19: =E19*1.13 -> 474.46782 | G19: =F19*1.13 -> 536.14864 | H19: =$B$19+(1.13)^6 -> 293.08195 | I19: =$B$19+(1.13)^7 -> 293.35261 | J19: =$B$19+(1.13)^8 -> 293.65844 | K19: =$B$19+(1.13)^9 -> 294.00404 | L19: =$B$19+(1.13)^10 -> 294.39457 | N19: The Units sold is increasing by 13% every year
A21: Calculation Refined Petroleum Sales Revenue | B21: 45658 | C21: 46023 | D21: 46388 | E21: 46753 | F21: 47119 | G21: 47484 | H21: 47849 | I21: 48214 | J21: 48580 | K21: 48945 | L21: 49310
A22: Premium for Refined Petroleum Products | B22: 0.17 | C22: 0.17 | D22: 0.17 | E22: 0.17 | F22: 0.17 | G22: 0.17 | H22: 0.17 | I22: 0.17 | J22: 0.17 | K22: 0.17 | L22: 0.17 | N22: Premium of the Refined Petroleum Products remain constant
A23: Price per Refined Petroleum Unit | B23: =B18+(B18*17%) -> 0 | C23: =C18+(C18*17%) -> 106.45927 | D23: =D18+(D18*17%) -> 111.88029 | E23: =E18+(E18*17%) -> 116.94947 | F23: =F18+(F18*17%) -> 121.81208 | G23: =G18+(G18*17%) -> 126.54476 | H23: =H18+(H18*17%) -> #REF! | I23: =I18+(I18*17%) -> #REF! | ... L23: =L18+(L18*17%) -> #REF! | N23: You will have to add 17% premium on the Current Crude Price
A24: Total Refined Petroleum Sales | B24: =B23*B19 -> 0 | C24: =C23*C19 -> 35007.001 | D24: =D23*D19 -> 41572.244 | E24: =E23*E19 -> 49105.099 | F24: =F23*F19 -> 57795.912 | G24: =G23*G19 -> 67846.799 | H24: =H23*H19 -> #REF! | I24: =I23*I19 -> #REF! | ... L24: =L23*L19 -> #REF! | N24: To find the Total Refined Petroleum Sales you will have to multiply the Units Sold with Price per Refined Petroleum Unit
A26: Calculation Material Expenses | B26: 45658 | C26: 46023 | D26: 46388 | E26: 46753 | F26: 47119 | G26: 47484 | H26: 47849 | I26: 48214 | J26: 48580 | K26: 48945 | L26: 49310
A27: Inventory (Units Sold) | B27: =B19 -> 291 | C27: =C19 -> 328.83 | D27: =D19 -> 371.5779 | E27: =E19 -> 419.88303 | F27: =F19 -> 474.46782 | G27: =G19 -> 536.14864 | H27: =H19 -> 293.08195 | I27: =I19 -> 293.35261 | ... L27: =L19 -> 294.39457 | N27: It’s the same as Units Sold
A28: Raw Crude Price | B28: =B18 -> 0 | C28: =C18 -> 90.990826 | D28: =D18 -> 95.624182 | E28: =E18 -> 99.956814 | F28: =F18 -> 104.11289 | G28: =G18 -> 108.15791 | H28: =H18 -> #REF! | I28: =I18 -> #REF! | ... L28: =L18 -> #REF! | N28: Is the the same as Current Crude Price
A29: Total Material Expenses | B29: =B27*B28 -> 0 | C29: =C27*C28 -> 29920.513 | D29: =D27*D28 -> 35531.833 | E29: =E27*E28 -> 41970.17 | F29: =F27*F28 -> 49398.216 | G29: =G27*G28 -> 57988.717 | H29: =H27*H28 -> #REF! | I29: =I27*I28 -> #REF! | ... L29: =L27*L28 -> #REF! | N29: Total Material Expenses is when you will have to multiply Raw Crude Price with Units sold.
A31: Pessimistic Scenario | B31: 45658 | C31: 46023 | D31: 46388 | E31: 46753 | F31: 47119 | G31: 47484 | H31: 47849 | I31: 48214 | J31: 48580 | K31: 48945 | L31: 49310
A32: Lower Confidence Level | C32: =VLOOKUP(C31,Forecast!A1:E1072,4,FALSE) -> 59.895338 | D32: =VLOOKUP(D31,Forecast!A1:E1096,4,FALSE) -> 57.522115 | E32: =VLOOKUP(E31,Forecast!A1:E1091,4,FALSE) -> 55.449616 | F32: =VLOOKUP(F31,Forecast!A1:E1051,4,FALSE) -> 53.553673 | G32: =VLOOKUP(G31,Forecast!A1:E1230,4,FALSE) -> 51.768784 | H32: =VLOOKUP(H3,#REF!,4,0) -> #REF! | I32: =VLOOKUP(I3,#REF!,4,0) -> #REF! | J32: =VLOOKUP(J3,#REF!,4,0) -> #REF! | K32: =VLOOKUP(K3,#REF!,4,0) -> #REF! | L32: =VLOOKUP(L3,#REF!,4,0) -> #REF! | N32: You will have to use the VLOOKUP Function here or manually enter the figures from the forecasting sheet
A33: Units Sold - Pessimistic | B33: 235 | C33: =B33*(1-8%) -> 216.2 | D33: =C33*(1-8%) -> 198.904 | E33: =D33*(1-8%) -> 182.99168 | F33: =E33*(1-8%) -> 168.35235 | G33: =F33*(1-8%) -> 154.88416 | H33: =$B$33+(1.13)^-6 -> 235.48032 | I33: =$B$33+(1.13)^-7 -> 235.42506 | J33: =$B$33+(1.13)^-8 -> 235.37616 | K33: =$B$33+(1.13)^-9 -> 235.33288 | L33: =$B$33+(1.13)^-10 -> 235.29459 | N33: The Units sold is decreasing by 8% every year
A35: Calculation Refined Petroleum Sales Revenue | B35: 45658 | C35: 46023 | D35: 46388 | E35: 46753 | F35: 47119 | G35: 47484 | H35: 47849 | I35: 48214 | J35: 48580 | K35: 48945 | L35: 49310
A36: Premium for Refined Petroleum Products | B36: 0.17 | C36: 0.17 | D36: 0.17 | E36: 0.17 | F36: 0.17 | G36: 0.17 | H36: 0.17 | I36: 0.17 | J36: 0.17 | K36: 0.17 | L36: 0.17 | N36: Premium of the Refined Petroleum Products remain constant
A37: Price per Refined Petroleum Unit | B37: =B32+(B32*17%) -> 0 | C37: =C32+(C32*17%) -> 70.077545 | D37: =D32+(D32*17%) -> 67.300874 | E37: =E32+(E32*17%) -> 64.87605 | F37: =F32+(F32*17%) -> 62.657798 | G37: =G32+(G32*17%) -> 60.569477 | H37: =H32+(H32*17%) -> #REF! | I37: =I32+(I32*17%) -> #REF! | ... L37: =L32+(L32*17%) -> #REF! | N37: You will have to add 17% premium on the Current Crude Price
A38: Total Refined Petroleum Sales | B38: =B37*B33 -> 0 | C38: =C37*C33 -> 15150.765 | D38: =D37*D33 -> 13386.413 | E38: =E37*E33 -> 11871.777 | F38: =F37*F33 -> 10548.587 | G38: =G37*G33 -> 9381.2524 | H38: =H37*H33 -> #REF! | I38: =I37*I33 -> #REF! | ... L38: =L37*L33 -> #REF! | N38: To find the Total Refined Petroleum Sales you will have to multiply the Units Sold with Price per Refined Petroleum Unit
A40: Calculation Material Expenses | B40: 45658 | C40: 46023 | D40: 46388 | E40: 46753 | F40: 47119 | G40: 47484 | H40: 47849 | I40: 48214 | J40: 48580 | K40: 48945 | L40: 49310
A41: Inventory (Units Sold) | B41: =B33 -> 235 | C41: =C33 -> 216.2 | D41: =D33 -> 198.904 | E41: =E33 -> 182.99168 | F41: =F33 -> 168.35235 | G41: =G33 -> 154.88416 | H41: =H33 -> 235.48032 | I41: =I33 -> 235.42506 | ... L41: =L33 -> 235.29459 | N41: It’s the same as Units Sold
A42: Raw Crude Price | B42: =B32 -> 0 | C42: =C32 -> 59.895338 | D42: =D32 -> 57.522115 | E42: =E32 -> 55.449616 | F42: =F32 -> 53.553673 | G42: =G32 -> 51.768784 | H42: =H32 -> #REF! | I42: =I32 -> #REF! | ... L42: =L32 -> #REF! | N42: Is the the same as Current Crude Price
A43: Total Material Expenses | B43: =B41*B42 -> 0 | C43: =C41*C42 -> 12949.372 | D43: =D41*D42 -> 11441.379 | E43: =E41*E42 -> 10146.818 | F43: =F41*F42 -> 9015.8865 | G43: =G41*G42 -> 8018.1645 | H43: =H41*H42 -> #REF! | I43: =I41*I42 -> #REF! | ... L43: =L41*L42 -> #REF! | N43: Total Material Expenses is when you will have to multiply Raw Crude Price with Units sold.
